{
  "appId": "com.castpark.voidbrowser",
  "productName": "VoidBrowser",
  "directories": {
    "output": "release-setup"
  },
  "files": [
    "**/*",
    "!release/**/*",
    "!release-single/**/*",
    "!release-setup/**/*",
    "!build/iexpress-stage/**/*",
    "!node_modules/.cache/**/*"
  ],
  "win": {
    "icon": "assets/icon.ico",
    "target": [
      {
        "target": "nsis",
        "arch": [
          "x64"
        ]
      }
    ],
    "signAndEditExecutable": false,
    "artifactName": "VoidBrowser-Setup-${version}.${ext}"
  },
  "nsis": {
    "oneClick": false,
    "allowToChangeInstallationDirectory": true,
    "deleteAppDataOnUninstall": false,
    "differentialPackage": false,
    "installerIcon": "assets/icon.ico",
    "uninstallerIcon": "assets/icon.ico",
    "installerHeaderIcon": "assets/icon.ico"
  },
  "publish": [
    {
      "provider": "github",
      "owner": "CastPark",
      "repo": "VoidBrowserCP",
      "releaseType": "release"
    }
  ]
}